ztfquery/__init__.py
ztfquery/alert.py
ztfquery/bts.py
ztfquery/buildurl.py
ztfquery/ccd.py
ztfquery/cluster.py
ztfquery/fields.py
ztfquery/filters.py
ztfquery/fritz.py
ztfquery/io.py
ztfquery/lightcurve.py
ztfquery/marshal.py
ztfquery/metasearch.py
ztfquery/photometry.py
ztfquery/planner.py
ztfquery/query.py
ztfquery/sedm.py
ztfquery/skyvision.py
ztfquery/ztftable.py
ztfquery/data/ZTF_corners_rcid.txt
ztfquery/data/filter_p48_g.dat
ztfquery/data/filter_p48_i.dat
ztfquery/data/filter_p48_r.dat
ztfquery/data/source
ztfquery/data/ztf_ccd_layout.tbl
ztfquery/data/ztf_ccd_quad_layout.tbl
ztfquery/data/ztf_fields.txt
ztfquery/utils/__init__.py
ztfquery/utils/plots.py
ztfquery/utils/stamps.py
ztfquery/utils/tools.py
ztfquery-1.28.0.dist-info/LICENSE
ztfquery-1.28.0.dist-info/METADATA
ztfquery-1.28.0.dist-info/WHEEL
ztfquery-1.28.0.dist-info/top_level.txt
ztfquery-1.28.0.dist-info/RECORD
